{
    "code": 200,
    "data": {
        "columns": [
            {
                "author": "美物娘",
                "banner_image_url": "http://img01.liwushuo.com/image/160608/8nluue8yx.jpg-w300",
                "banner_webp_url": "http://img01.liwushuo.com/image/160608/8nluue8yx.jpg?imageView2/2/w/300/q/85/format/webp",
                "category": "美物",
                "cover_image_url": "http://img03.liwushuo.com/image/160713/zlsbvl5it.jpg-w720",
                "cover_webp_url": "http://img03.liwushuo.com/image/160713/zlsbvl5it.jpg?imageView2/2/w/720/q/85/format/webp",
                "created_at": 1462501829,
                "description": "贪念时间所有美好的东西，唯一不吝啬的，就是与你分享。",
                "id": 19,
                "order": 0,
                "post_published_at": 1492052400,
                "status": 0,
                "subtitle": "",
                "title": "美物收割机",
                "updated_at": 1491903752
            },
            {
                "author": "小爱",
                "banner_image_url": "http://img02.liwushuo.com/image/160706/bsfcyilj0.jpg-w300",
                "banner_webp_url": "http://img02.liwushuo.com/image/160706/bsfcyilj0.jpg?imageView2/2/w/300/q/85/format/webp",
                "category": "礼物",
                "cover_image_url": "http://img03.liwushuo.com/image/160713/nkxdwgmos.jpg-w720",
                "cover_webp_url": "http://img03.liwushuo.com/image/160713/nkxdwgmos.jpg?imageView2/2/w/720/q/85/format/webp",
                "created_at": 1467783110,
                "description": "在这里，满满都是我对你的爱。",
                "id": 88,
                "order": 0,
                "post_published_at": 1492052400,
                "status": 0,
                "subtitle": "",
                "title": "甜蜜礼物社",
                "updated_at": 1491903659
            },
            {
                "author": "灰姑娘",
                "banner_image_url": "http://img03.liwushuo.com/image/160608/qojypq4pe.jpg-w300",
                "banner_webp_url": "http://img03.liwushuo.com/image/160608/qojypq4pe.jpg?imageView2/2/w/300/q/85/format/webp",
                "category": "美护",
                "cover_image_url": "http://img01.liwushuo.com/image/160713/en5n83z34.jpg-w720",
                "cover_webp_url": "http://img01.liwushuo.com/image/160713/en5n83z34.jpg?imageView2/2/w/720/q/85/format/webp",
                "created_at": 1462501946,
                "description": "好看就行。——玛丽莲·赫本·千颂伊",
                "id": 23,
                "order": 0,
                "post_published_at": 1492041600,
                "status": 0,
                "subtitle": "",
                "title": "靠脸吃饭",
                "updated_at": 1491903569
            },
            {
                "author": "穿衣大队长",
                "banner_image_url": "http://img03.liwushuo.com/image/160608/ygqtl238c.jpg-w300",
                "banner_webp_url": "http://img03.liwushuo.com/image/160608/ygqtl238c.jpg?imageView2/2/w/300/q/85/format/webp",
                "category": "穿搭",
                "cover_image_url": "http://img03.liwushuo.com/image/160713/4egoefdla.jpg-w720",
                "cover_webp_url": "http://img03.liwushuo.com/image/160713/4egoefdla.jpg?imageView2/2/w/720/q/85/format/webp",
                "created_at": 1462501669,
                "description": "做你的私人搭配师，精心搭配治好你的选择困难症，满足你多睡5分钟的小小心愿。",
                "id": 13,
                "order": 0,
                "post_published_at": 1492041600,
                "status": 0,
                "subtitle": "",
                "title": "明天穿什么",
                "updated_at": 1491903488
            },
            {
                "author": "小礼君",
                "banner_image_url": "http://img03.liwushuo.com/image/170119/gjv9kljjh.jpg-w300",
                "banner_webp_url": "http://img03.liwushuo.com/image/170119/gjv9kljjh.jpg?imageView2/2/w/300/q/85/format/webp",
                "category": "礼物",
                "cover_image_url": "http://img01.liwushuo.com/image/161219/0kmwa8wby.jpg-w720",
                "cover_webp_url": "http://img01.liwushuo.com/image/161219/0kmwa8wby.jpg?imageView2/2/w/720/q/85/format/webp",
                "created_at": 1482140135,
                "description": "职场人士必备贴",
                "id": 122,
                "order": 0,
                "post_published_at": 1491966000,
                "status": 0,
                "subtitle": "礼物",
                "title": "因礼不同",
                "updated_at": 1491879260
            },
            {
                "author": "资优生",
                "banner_image_url": "http://img01.liwushuo.com/image/160701/39gumoiqc.jpg-w300",
                "banner_webp_url": "http://img01.liwushuo.com/image/160701/39gumoiqc.jpg?imageView2/2/w/300/q/85/format/webp",
                "category": "美护",
                "cover_image_url": "http://img01.liwushuo.com/image/160713/o9rsmpl0c.jpg-w720",
                "cover_webp_url": "http://img01.liwushuo.com/image/160713/o9rsmpl0c.jpg?imageView2/2/w/720/q/85/format/webp",
                "created_at": 1467340938,
                "description": "iPhone腿、A4腰、锁骨放硬币、反手摸肚脐\r\n没有最严苛的审美，只有最病态的减肥！\r\n还是既健康又美丽来的实际！",
                "id": 85,
                "order": 0,
                "post_published_at": 1491879600,
                "status": 0,
                "subtitle": "",
                "title": "美体小铺",
                "updated_at": 1491874809
            },
            {
                "author": "小礼君",
                "banner_image_url": "http://img03.liwushuo.com/image/160905/f5g5ouwkz.jpg-w300",
                "banner_webp_url": "http://img03.liwushuo.com/image/160905/f5g5ouwkz.jpg?imageView2/2/w/300/q/85/format/webp",
                "category": "礼物",
                "cover_image_url": "http://img02.liwushuo.com/image/160905/xqyvy9n1z.jpg-w720",
                "cover_webp_url": "http://img02.liwushuo.com/image/160905/xqyvy9n1z.jpg?imageView2/2/w/720/q/85/format/webp",
                "created_at": 1473045022,
                "description": "动心的太多，走心的1个足矣",
                "id": 106,
                "order": 0,
                "post_published_at": 1491523200,
                "status": 0,
                "subtitle": "",
                "title": "一个",
                "updated_at": 1491468421
            },
            {
                "author": "小礼君",
                "banner_image_url": "http://img02.liwushuo.com/image/160902/fm7knqhbd.jpg-w300",
                "banner_webp_url": "http://img02.liwushuo.com/image/160902/fm7knqhbd.jpg?imageView2/2/w/300/q/85/format/webp",
                "category": "美护",
                "cover_image_url": "http://img03.liwushuo.com/image/160902/7obqmumbf.jpg-w720",
                "cover_webp_url": "http://img03.liwushuo.com/image/160902/7obqmumbf.jpg?imageView2/2/w/720/q/85/format/webp",
                "created_at": 1472820604,
                "description": "明星的美丽秘诀永远是大家最感兴趣的话题之一，现在就让我们一一揭秘。",
                "id": 105,
                "order": 0,
                "post_published_at": 1491361200,
                "status": 0,
                "subtitle": "",
                "title": "星美妆报告",
                "updated_at": 1491042790
            },
            {
                "author": "上上签",
                "banner_image_url": "http://img01.liwushuo.com/image/160902/9u68tzum1.jpg-w300",
                "banner_webp_url": "http://img01.liwushuo.com/image/160902/9u68tzum1.jpg?imageView2/2/w/300/q/85/format/webp",
                "category": "美物",
                "cover_image_url": "http://img02.liwushuo.com/image/160902/gsscbi494.jpg-w720",
                "cover_webp_url": "http://img02.liwushuo.com/image/160902/gsscbi494.jpg?imageView2/2/w/720/q/85/format/webp",
                "created_at": 1472785741,
                "description": "把对你的爱，写进365首诗里、歌里拥入365天的心里、梦里。",
                "id": 96,
                "order": 0,
                "post_published_at": 1490745600,
                "status": 0,
                "subtitle": "",
                "title": "日复一签",
                "updated_at": 1490701519
            },
            {
                "author": "小C",
                "banner_image_url": "http://img03.liwushuo.com/image/160608/kd1dy4pi3.jpg-w300",
                "banner_webp_url": "http://img03.liwushuo.com/image/160608/kd1dy4pi3.jpg?imageView2/2/w/300/q/85/format/webp",
                "category": "礼物",
                "cover_image_url": "http://img01.liwushuo.com/image/160713/y2arp77qx.jpg-w720",
                "cover_webp_url": "http://img01.liwushuo.com/image/160713/y2arp77qx.jpg?imageView2/2/w/720/q/85/format/webp",
                "created_at": 1462501381,
                "description": "如果青春不会散场，时光可以珍藏。如果你的每一个米粒大小念想，都能找到与之匹配的美物安放...这样的店你会不会来？",
                "id": 5,
                "order": 0,
                "post_published_at": 1490666400,
                "status": 0,
                "subtitle": "",
                "title": "不打烊的礼物店",
                "updated_at": 1490616463
            },
            {
                "author": "小礼君",
                "banner_image_url": "http://img03.liwushuo.com/image/160815/v2p80ao8y.jpg-w300",
                "banner_webp_url": "http://img03.liwushuo.com/image/160815/v2p80ao8y.jpg?imageView2/2/w/300/q/85/format/webp",
                "category": "礼物",
                "cover_image_url": "http://img01.liwushuo.com/image/160815/fervz0o5x.jpg-w720",
                "cover_webp_url": "http://img01.liwushuo.com/image/160815/fervz0o5x.jpg?imageView2/2/w/720/q/85/format/webp",
                "created_at": 1471225655,
                "description": "品质、考究、精心遴选；细节、严格、甄添筛减；处女座强迫症的挑选小组，一份有态度的最佳礼物大赏。",
                "id": 94,
                "order": 0,
                "post_published_at": 1490572800,
                "status": 0,
                "subtitle": "",
                "title": "最佳礼物大赏",
                "updated_at": 1490613768
            }
        ],
        "paging": {
            "next_url": "http://api.liwushuo.com/v2/columns?limit=11&offset=11"
        }
    },
    "message": "OK"
}